itsfm/__init__.py
itsfm/__main__.py
itsfm/batch_processing.py
itsfm/combine_segmentation_measurement.py
itsfm/data_contributors.csv
itsfm/frequency_tracking.py
itsfm/measure.py
itsfm/measurement_functions.py
itsfm/refine_cfm_regions.py
itsfm/run_example_analysis.py
itsfm/sanity_checks.py
itsfm/segment.py
itsfm/signal_cleaning.py
itsfm/signal_processing.py
itsfm/simulate_calls.py
itsfm/user_interface.py
itsfm/view.py
itsfm/data/685_GAP_Calls_G2019-04-03_23-48-40_0077_2.wav
itsfm/data/ACTxx_2019-03-28_10-16-10_0000001 1.wav
itsfm/data/GG-USG2017-03-17_20-27-53_0038verygood.wav
itsfm/data/GG2018-03-20_19-31-34_062.wav
itsfm/data/Pachycephala_pectoralis_flavotincta_IS-F-Raren_19970809_S1_ATC.wav
itsfm/data/Rhinolophus_refulgens_RHRE92VA_20kHzHP_0.wav
itsfm/data/XC446904-DismentalisMIStape11-2.wav
itsfm/data/XC446904-DismentalisMIStape11.wav
itsfm/data/__init__.py
itsfm/data/__init__.pyc
itsfm/data/matching_annotaudio_Aditya_2018-08-17_23_115.WAV
itsfm/data/matching_annotaudio_Aditya_2018-08-17_23_14.WAV
itsfm/data/matching_annotaudio_Aditya_2018-08-17_23_141.WAV
itsfm/data/matching_annotaudio_Aditya_2018-08-17_23_157.WAV
itsfm/data/matching_annotaudio_Aditya_2018-08-17_23_173.WAV
itsfm/data/matching_annotaudio_Aditya_2018-08-17_23_196.WAV
itsfm/data/matching_annotaudio_Aditya_2018-08-17_23_24.WAV
itsfm/data/matching_annotaudio_Aditya_2018-08-17_23_56.WAV
itsfm/data/matching_annotaudio_Aditya_2018-08-17_23_65.WAV
itsfm/data/matching_annotaudio_Aditya_2018-08-17_23_70.WAV
itsfm/data/matching_annotaudio_Aditya_2018-08-17_34_1.WAV
itsfm/data/matching_annotaudio_Aditya_2018-08-17_34_111.WAV
itsfm/data/matching_annotaudio_Aditya_2018-08-17_34_12.WAV
itsfm/data/matching_annotaudio_Aditya_2018-08-17_34_120.WAV
itsfm/data/matching_annotaudio_Aditya_2018-08-17_34_132.WAV
itsfm/data/matching_annotaudio_Aditya_2018-08-17_34_133.WAV
itsfm/data/matching_annotaudio_Aditya_2018-08-17_34_134.WAV
itsfm/data/matching_annotaudio_Aditya_2018-08-17_34_142.WAV
itsfm-0.1.0.dist-info/LICENSE
itsfm-0.1.0.dist-info/METADATA
itsfm-0.1.0.dist-info/WHEEL
itsfm-0.1.0.dist-info/top_level.txt
itsfm-0.1.0.dist-info/RECORD
